loxws/__init__.py
loxws/configdata.py
loxws/loxalarmclock.py
loxws/loxclimatecontroller.py
loxws/loxcolorpickerv2.py
loxws/loxdimmer.py
loxws/loxgate.py
loxws/loxinfoonlyanalog.py
loxws/loxinfoonlydigital.py
loxws/loxiroomcontrollerv2.py
loxws/loxjalousie.py
loxws/loxlightcontrollerv2.py
loxws/loxmeter.py
loxws/loxpresencedetector.py
loxws/loxswitch.py
loxws/loxwindow.py
loxws/messagebody.py
loxws/messageheader.py
loxws/miniserver.py
loxws/wsclient.py
loxws-0.0.60.dist-info/LICENSE
loxws-0.0.60.dist-info/METADATA
loxws-0.0.60.dist-info/WHEEL
loxws-0.0.60.dist-info/top_level.txt
loxws-0.0.60.dist-info/RECORD
