Metadata-Version: 2.1
Name: loxws
Version: 0.0.60
Summary: Loxone Client
Home-page: https://github.com/grimbouk/loxws
Author: tjsmithuk
Author-email: tjsmithuk@clamfish.com
Classifier: Programming Language :: Python :: 3
Classifier: License :: OSI Approved :: MIT License
Classifier: Operating System :: OS Independent
License-File: LICENSE
Requires-Dist: pycryptodome >=3.14.1
Requires-Dist: aiohttp >=3.9.1
